LiyongPythonJinxingShujufenxiDi2BanFix1Fix1/README.md
LiyongPythonJinxingShujufenxiDi2BanFix1Fix1/__init__.py
LiyongPythonJinxingShujufenxiDi2BanFix1Fix1/__main__.py
LiyongPythonJinxingShujufenxiDi2BanFix1Fix1/file.epub
LiyongPythonJinxingShujufenxiDi2BanFix1Fix1/index.html
LiyongPythonJinxingShujufenxiDi2BanFix1Fix1/css/__init__.py
LiyongPythonJinxingShujufenxiDi2BanFix1Fix1/css/annotations.css
LiyongPythonJinxingShujufenxiDi2BanFix1Fix1/css/main.css
LiyongPythonJinxingShujufenxiDi2BanFix1Fix1/css/normalize.css
LiyongPythonJinxingShujufenxiDi2BanFix1Fix1/css/popup.css
LiyongPythonJinxingShujufenxiDi2BanFix1Fix1/font/__init__.py
LiyongPythonJinxingShujufenxiDi2BanFix1Fix1/font/fontello.eot
LiyongPythonJinxingShujufenxiDi2BanFix1Fix1/font/fontello.svg
LiyongPythonJinxingShujufenxiDi2BanFix1Fix1/font/fontello.ttf
LiyongPythonJinxingShujufenxiDi2BanFix1Fix1/font/fontello.woff
LiyongPythonJinxingShujufenxiDi2BanFix1Fix1/img/__init__.py
LiyongPythonJinxingShujufenxiDi2BanFix1Fix1/img/annotator-glyph-sprite.png
LiyongPythonJinxingShujufenxiDi2BanFix1Fix1/img/annotator-icon-sprite.png
LiyongPythonJinxingShujufenxiDi2BanFix1Fix1/img/apple-touch-icon.png
LiyongPythonJinxingShujufenxiDi2BanFix1Fix1/img/cancelfullscreen.png
LiyongPythonJinxingShujufenxiDi2BanFix1Fix1/img/close.png
LiyongPythonJinxingShujufenxiDi2BanFix1Fix1/img/fullscreen.png
LiyongPythonJinxingShujufenxiDi2BanFix1Fix1/img/loader.gif
LiyongPythonJinxingShujufenxiDi2BanFix1Fix1/img/menu-icon.png
LiyongPythonJinxingShujufenxiDi2BanFix1Fix1/img/save.png
LiyongPythonJinxingShujufenxiDi2BanFix1Fix1/img/saved.png
LiyongPythonJinxingShujufenxiDi2BanFix1Fix1/img/settings-s.png
LiyongPythonJinxingShujufenxiDi2BanFix1Fix1/img/settings.png
LiyongPythonJinxingShujufenxiDi2BanFix1Fix1/img/star.png
LiyongPythonJinxingShujufenxiDi2BanFix1Fix1/js/__init__.py
LiyongPythonJinxingShujufenxiDi2BanFix1Fix1/js/epub.js
LiyongPythonJinxingShujufenxiDi2BanFix1Fix1/js/epub.min.js
liyong_python_jinxing_shujufenxi_di_2_ban_fix1_fix1-2025.3.25.1.dist-info/METADATA
liyong_python_jinxing_shujufenxi_di_2_ban_fix1_fix1-2025.3.25.1.dist-info/WHEEL
liyong_python_jinxing_shujufenxi_di_2_ban_fix1_fix1-2025.3.25.1.dist-info/entry_points.txt
liyong_python_jinxing_shujufenxi_di_2_ban_fix1_fix1-2025.3.25.1.dist-info/top_level.txt
liyong_python_jinxing_shujufenxi_di_2_ban_fix1_fix1-2025.3.25.1.dist-info/RECORD
